osman/VAE_model_noCat.py
osman/WGAN_model.py
osman/__init__.py
osman/helpers.py
osman/oversampler.py
osman-0.0.1.dist-info/LICENSE
osman-0.0.1.dist-info/METADATA
osman-0.0.1.dist-info/WHEEL
osman-0.0.1.dist-info/top_level.txt
osman-0.0.1.dist-info/RECORD
