Metadata-Version: 2.1
Name: osman
Version: 0.0.1
Summary: A package which lets users oversample class imbalanced(binary) data by Deep Generative Models. It offers two APIS. They are : variational auto encoder and WGAN-GP.
Author-email: Rafat Ashraf Joy <rafat.joy99@gmail.com>
Project-URL: Homepage, https://github.com/rajoy99/osman
Project-URL: Bug Tracker, https://github.com/rajoy99/osman/issues
Classifier: Programming Language :: Python :: 3
Classifier: License :: OSI Approved :: MIT License
Classifier: Operating System :: OS Independent
Requires-Python: >=3.7
License-File: LICENSE
Requires-Dist: torch
Requires-Dist: numpy
Requires-Dist: pandas
Requires-Dist: matplotlib
Requires-Dist: seaborn
Requires-Dist: scikit-learn
Requires-Dist: pathlib
Requires-Dist: imblearn
